geoedemo/__init__.py
geoedemo/geoedemo.py
geoedemo-0.0.2.dist-info/LICENSE
geoedemo-0.0.2.dist-info/METADATA
geoedemo-0.0.2.dist-info/WHEEL
geoedemo-0.0.2.dist-info/top_level.txt
geoedemo-0.0.2.dist-info/RECORD
