Metadata-Version: 2.1
Name: geoedemo
Version: 0.0.2
Summary: Python package musings for geo
Home-page: https://github.com/shakurgds/geoedemo
Author: shakur
Author-email: shakurgds@gmail.com
License: MIT license
Keywords: geoedemo
Platform: UNKNOWN
Classifier: Development Status :: 2 - Pre-Alpha
Classifier: Intended Audience :: Developers
Classifier: License :: OSI Approved :: MIT License
Classifier: Natural Language :: English
Classifier: Programming Language :: Python :: 3
Classifier: Programming Language :: Python :: 3.5
Classifier: Programming Language :: Python :: 3.6
Classifier: Programming Language :: Python :: 3.7
Classifier: Programming Language :: Python :: 3.8
Requires-Python: >=3.5
